xnlpy/__init__.py
xnlpy/xnlpy.cpython-310-x86_64-linux-gnu.so
xnlpy-0.1.2.3.dist-info/LICENSE
xnlpy-0.1.2.3.dist-info/METADATA
xnlpy-0.1.2.3.dist-info/WHEEL
xnlpy-0.1.2.3.dist-info/top_level.txt
xnlpy-0.1.2.3.dist-info/RECORD
