Metadata-Version: 2.1
Name: xnlpy
Version: 0.1.2.3
Summary: Biblioteca para realização de cálculos numéricos
Author-email: Gilberto José Guimarães de Sousa Mourão <gilbertojos.mourao@gmail.com>
Maintainer-email: Gilberto José Guimarães de Sousa Mourão <gilbertojos.mourao@gmail.com>
License: MIT License
Project-URL: Homepage, https://github.com/gilbertomourao/xnlpy
Project-URL: Repository, https://github.com/gilbertomourao/xnlpy
Project-URL: Issues, https://github.com/gilbertomourao/xnlpy/issues
Keywords: xnlpy,calculus,numerical
Classifier: Programming Language :: Python :: 3
Classifier: License :: OSI Approved :: MIT License
Classifier: Operating System :: POSIX :: Linux
Requires-Python: >=3.10
License-File: LICENSE
